arcane/bigquery.py
arcane/validation.py
arcane_bigquery-2.3.1.dist-info/METADATA
arcane_bigquery-2.3.1.dist-info/WHEEL
arcane_bigquery-2.3.1.dist-info/RECORD
