Metadata-Version: 2.3
Name: arcane-bigquery
Version: 2.3.1
Summary: Override google bigquery python client
Author: Arcane
Author-email: product@wearcane.com
Requires-Python: >=3.9,<3.14
Classifier: Programming Language :: Python :: 3
Classifier: Programming Language :: Python :: 3.9
Classifier: Programming Language :: Python :: 3.10
Classifier: Programming Language :: Python :: 3.11
Classifier: Programming Language :: Python :: 3.12
Classifier: Programming Language :: Python :: 3.13
Requires-Dist: arcane-core (>=1.6.0,<2.0.0)
Requires-Dist: backoff (>=1.10.0)
Requires-Dist: google-cloud-bigquery (>=3.34.0,<4.0.0)
